[
    {
        "release": "2020.Q2.G.03",
        "country_code": "654",
        "country_name": "Saint Helena",
        "indicator_code": "C010401",
        "indicator_reference": "1.4.1",
        "seriesCode": "SP_ACS_BSRVH2O",
        "seriesDescription": "Proportion of population using basic drinking water services, by location (%)",
        "timeSeriesTitle": "Proportion of population using basic drinking water services",
        "timeSeriesUnit": "percent",
        "hub": "da7d9e13a45b4734b5eef4b8355cdb6c",
        "dashboard": "",
        "slice_dimensions": {
            "location_code": "_T"
        },
        "data_values": [
            "98.5",
            "98.5",
            "98.5",
            "98.5",
            "98.5",
            "98.55",
            "98.6",
            "98.65",
            "98.7",
            "98.75",
            "98.8",
            "98.85",
            "98.9",
            "98.95",
            "99.0",
            "99.05"
        ],
        "data_years": [
            2002,
            2003,
            2004,
            2005,
            2006,
            2007,
            2008,
            2009,
            2010,
            2011,
            2012,
            2013,
            2014,
            2015,
            2016,
            2017
        ],
        "data_is_censored": [
            false,
            false,
            false,
            false,
            false,
            false,
            false,
            false,
            false,
            false,
            false,
            false,
            false,
            false,
            false,
            false
        ],
        "data_numeric_part": [
            98.5,
            98.5,
            98.5,
            98.5,
            98.5,
            98.55,
            98.6,
            98.65,
            98.7,
            98.75,
            98.8,
            98.85,
            98.9,
            98.95,
            99.0,
            99.05
        ],
        "preferred_visualization": null
    },
    {
        "release": "2020.Q2.G.03",
        "country_code": "654",
        "country_name": "Saint Helena",
        "indicator_code": "C010401",
        "indicator_reference": "1.4.1",
        "seriesCode": "SP_ACS_BSRVSAN",
        "seriesDescription": "Proportion of population using basic sanitation services, by location (%)",
        "timeSeriesTitle": "Proportion of population using basic sanitation services",
        "timeSeriesUnit": "percent",
        "hub": "1df36f26cad44482b56e0f6e5ad471dd",
        "dashboard": "",
        "slice_dimensions": {
            "location_code": "_T"
        },
        "data_values": [
            "98.875",
            "98.875",
            "98.875",
            "98.875",
            "98.875",
            "98.9875",
            "99.1",
            "99.2125",
            "99.325",
            "99.4375",
            "99.55",
            "99.6625",
            "99.775",
            "99.8875",
            "100.0",
            "100.0"
        ],
        "data_years": [
            2002,
            2003,
            2004,
            2005,
            2006,
            2007,
            2008,
            2009,
            2010,
            2011,
            2012,
            2013,
            2014,
            2015,
            2016,
            2017
        ],
        "data_is_censored": [
            false,
            false,
            false,
            false,
            false,
            false,
            false,
            false,
            false,
            false,
            false,
            false,
            false,
            false,
            false,
            false
        ],
        "data_numeric_part": [
            98.875,
            98.875,
            98.875,
            98.875,
            98.875,
            98.9875,
            99.1,
            99.2125,
            99.325,
            99.4375,
            99.55,
            99.6625,
            99.775,
            99.8875,
            100.0,
            100.0
        ],
        "preferred_visualization": null
    },
    {
        "release": "2020.Q2.G.03",
        "country_code": "654",
        "country_name": "Saint Helena",
        "indicator_code": "C050c01",
        "indicator_reference": "5.c.1",
        "seriesCode": "SG_GEN_EQPWN",
        "seriesDescription": "Proportion of countries with systems to track and make public allocations for gender equality and women's empowerment (%)",
        "timeSeriesTitle": "Availability of systems to track and make public allocations for gender equality and women's empowerment",
        "timeSeriesUnit": "yes/no",
        "hub": "e12401453c6f498dbda5661d5e8c0001",
        "dashboard": "",
        "slice_dimensions": {},
        "data_values": [
            "0.0"
        ],
        "data_years": [
            2018
        ],
        "data_is_censored": [
            false
        ],
        "data_numeric_part": [
            0.0
        ],
        "preferred_visualization": null
    },
    {
        "release": "2020.Q2.G.03",
        "country_code": "654",
        "country_name": "Saint Helena",
        "indicator_code": "C060101",
        "indicator_reference": "6.1.1",
        "seriesCode": "SH_H2O_SAFE",
        "seriesDescription": "Proportion of population using safely managed drinking water services, by urban/rural (%)",
        "timeSeriesTitle": "Proportion of population using safely managed drinking water services",
        "timeSeriesUnit": "percent",
        "hub": "4b35638694f44c7e9add3f7d7e551b45",
        "dashboard": "",
        "slice_dimensions": {
            "location_code": "_T"
        },
        "data_values": [
            "88.6894",
            "88.6894",
            "88.6894",
            "88.6894",
            "88.6894",
            "88.73442",
            "88.77944",
            "88.82446",
            "88.86948",
            "88.9145",
            "88.95952",
            "89.00454",
            "89.04956",
            "89.09458",
            "89.1396",
            "89.18462"
        ],
        "data_years": [
            2002,
            2003,
            2004,
            2005,
            2006,
            2007,
            2008,
            2009,
            2010,
            2011,
            2012,
            2013,
            2014,
            2015,
            2016,
            2017
        ],
        "data_is_censored": [
            false,
            false,
            false,
            false,
            false,
            false,
            false,
            false,
            false,
            false,
            false,
            false,
            false,
            false,
            false,
            false
        ],
        "data_numeric_part": [
            88.6894,
            88.6894,
            88.6894,
            88.6894,
            88.6894,
            88.73442,
            88.77944,
            88.82446,
            88.86948,
            88.9145,
            88.95952,
            89.00454,
            89.04956,
            89.09458,
            89.1396,
            89.18462
        ],
        "preferred_visualization": null
    },
    {
        "release": "2020.Q2.G.03",
        "country_code": "654",
        "country_name": "Saint Helena",
        "indicator_code": "C060201",
        "indicator_reference": "6.2.1",
        "seriesCode": "SH_SAN_DEFECT",
        "seriesDescription": "Proportion of population practicing open defecation, by urban/rural (%)",
        "timeSeriesTitle": "Proportion of population practicing open defecation",
        "timeSeriesUnit": "percent",
        "hub": "1232697c70f44d58ae0611f3f186a1f9",
        "dashboard": "",
        "slice_dimensions": {
            "location_code": "_T"
        },
        "data_values": [
            "0.0",
            "0.0",
            "0.0",
            "0.0",
            "0.0",
            "0.0",
            "0.0",
            "0.0",
            "0.0",
            "0.0",
            "0.0",
            "0.0",
            "0.0",
            "0.0",
            "0.0",
            "0.0"
        ],
        "data_years": [
            2002,
            2003,
            2004,
            2005,
            2006,
            2007,
            2008,
            2009,
            2010,
            2011,
            2012,
            2013,
            2014,
            2015,
            2016,
            2017
        ],
        "data_is_censored": [
            false,
            false,
            false,
            false,
            false,
            false,
            false,
            false,
            false,
            false,
            false,
            false,
            false,
            false,
            false,
            false
        ],
        "data_numeric_part": [
            0.0,
            0.0,
            0.0,
            0.0,
            0.0,
            0.0,
            0.0,
            0.0,
            0.0,
            0.0,
            0.0,
            0.0,
            0.0,
            0.0,
            0.0,
            0.0
        ],
        "preferred_visualization": null
    },
    {
        "release": "2020.Q2.G.03",
        "country_code": "654",
        "country_name": "Saint Helena",
        "indicator_code": "C060601",
        "indicator_reference": "6.6.1",
        "seriesCode": "EN_WBE_PMPR",
        "seriesDescription": "Water body extent (permanent) (% of total land area)",
        "timeSeriesTitle": "Permanent water body extent as a proportion of total land area",
        "timeSeriesUnit": "percent",
        "hub": "0ed77995dddc4205b9b149105241b954",
        "dashboard": "",
        "slice_dimensions": {},
        "data_values": [
            "0.0236592307692308",
            "0.0236592307692308",
            "0.0135489743589744",
            "0.0135489743589744",
            "0.0118289743589744",
            "0.0118289743589744",
            "0.0118289743589744",
            "0.0754412820512821",
            "0.138706153846153",
            "0.22430282051282",
            "0.309143076923076",
            "0.406670769230769"
        ],
        "data_years": [
            2005,
            2006,
            2007,
            2008,
            2011,
            2012,
            2013,
            2014,
            2015,
            2016,
            2017,
            2018
        ],
        "data_is_censored": [
            false,
            false,
            false,
            false,
            false,
            false,
            false,
            false,
            false,
            false,
            false,
            false
        ],
        "data_numeric_part": [
            0.0236592307692308,
            0.0236592307692308,
            0.0135489743589744,
            0.0135489743589744,
            0.0118289743589744,
            0.0118289743589744,
            0.0118289743589744,
            0.0754412820512821,
            0.138706153846153,
            0.22430282051282,
            0.309143076923076,
            0.406670769230769
        ],
        "preferred_visualization": null
    },
    {
        "release": "2020.Q2.G.03",
        "country_code": "654",
        "country_name": "Saint Helena",
        "indicator_code": "C060601",
        "indicator_reference": "6.6.1",
        "seriesCode": "EN_WBE_PMNR",
        "seriesDescription": "Water body extent (permanent) (square kilometres)",
        "timeSeriesTitle": "Permanent water body extent",
        "timeSeriesUnit": "square kilometers",
        "hub": "aa4c4097e8e846aab6f3a0b5e0879abc",
        "dashboard": "",
        "slice_dimensions": {},
        "data_values": [
            "0.092271",
            "0.092271",
            "0.052841",
            "0.052841",
            "0.046133",
            "0.046133",
            "0.046133",
            "0.294221",
            "0.540954",
            "0.874781",
            "1.205658",
            "1.586016"
        ],
        "data_years": [
            2005,
            2006,
            2007,
            2008,
            2011,
            2012,
            2013,
            2014,
            2015,
            2016,
            2017,
            2018
        ],
        "data_is_censored": [
            false,
            false,
            false,
            false,
            false,
            false,
            false,
            false,
            false,
            false,
            false,
            false
        ],
        "data_numeric_part": [
            0.092271,
            0.092271,
            0.052841,
            0.052841,
            0.046133,
            0.046133,
            0.046133,
            0.294221,
            0.540954,
            0.874781,
            1.205658,
            1.586016
        ],
        "preferred_visualization": null
    },
    {
        "release": "2020.Q2.G.03",
        "country_code": "654",
        "country_name": "Saint Helena",
        "indicator_code": "C060601",
        "indicator_reference": "6.6.1",
        "seriesCode": "EN_WBE_PMPP",
        "seriesDescription": "Water body extent (permanent and maybe permanent) (% of total land area)",
        "timeSeriesTitle": "Permanent and maybe permanent water body extent as a proportion of total land area",
        "timeSeriesUnit": "percent",
        "hub": "96b79a3017e14046a0df4e3eb06f6046",
        "dashboard": "",
        "slice_dimensions": {},
        "data_values": [
            "0.44169641025641",
            "0.460475128205128",
            "0.479457435897435",
            "0.479457435897435",
            "0.493929743589743",
            "0.493929743589743",
            "0.463591025641025",
            "0.463591025641025",
            "0.463591025641025",
            "0.456900769230769",
            "0.42754",
            "0.466904871794871",
            "0.474953076923076",
            "0.485495641025641"
        ],
        "data_years": [
            2005,
            2006,
            2007,
            2008,
            2009,
            2010,
            2011,
            2012,
            2013,
            2014,
            2015,
            2016,
            2017,
            2018
        ],
        "data_is_censored": [
            false,
            false,
            false,
            false,
            false,
            false,
            false,
            false,
            false,
            false,
            false,
            false,
            false,
            false
        ],
        "data_numeric_part": [
            0.44169641025641,
            0.460475128205128,
            0.479457435897435,
            0.479457435897435,
            0.493929743589743,
            0.493929743589743,
            0.463591025641025,
            0.463591025641025,
            0.463591025641025,
            0.456900769230769,
            0.42754,
            0.466904871794871,
            0.474953076923076,
            0.485495641025641
        ],
        "preferred_visualization": null
    },
    {
        "release": "2020.Q2.G.03",
        "country_code": "654",
        "country_name": "Saint Helena",
        "indicator_code": "C060601",
        "indicator_reference": "6.6.1",
        "seriesCode": "EN_WBE_PMPN",
        "seriesDescription": "Water body extent (permanent and maybe permanent) (square kilometres)",
        "timeSeriesTitle": "Permanent and maybe permanent water body extent",
        "timeSeriesUnit": "square kilometers",
        "hub": "bb2c237b99c54184800ed86fdaa3c5a4",
        "dashboard": "",
        "slice_dimensions": {},
        "data_values": [
            "1.722616",
            "1.795853",
            "1.869884",
            "1.869884",
            "1.926326",
            "1.926326",
            "1.808005",
            "1.808005",
            "1.808005",
            "1.781913",
            "1.667406",
            "1.820929",
            "1.852317",
            "1.893433"
        ],
        "data_years": [
            2005,
            2006,
            2007,
            2008,
            2009,
            2010,
            2011,
            2012,
            2013,
            2014,
            2015,
            2016,
            2017,
            2018
        ],
        "data_is_censored": [
            false,
            false,
            false,
            false,
            false,
            false,
            false,
            false,
            false,
            false,
            false,
            false,
            false,
            false
        ],
        "data_numeric_part": [
            1.722616,
            1.795853,
            1.869884,
            1.869884,
            1.926326,
            1.926326,
            1.808005,
            1.808005,
            1.808005,
            1.781913,
            1.667406,
            1.820929,
            1.852317,
            1.893433
        ],
        "preferred_visualization": null
    },
    {
        "release": "2020.Q2.G.03",
        "country_code": "654",
        "country_name": "Saint Helena",
        "indicator_code": "C070201",
        "indicator_reference": "7.2.1",
        "seriesCode": "EG_FEC_RNEW",
        "seriesDescription": "Renewable energy share in the total final energy consumption (%)",
        "timeSeriesTitle": "Renewable energy share in the total final energy consumption",
        "timeSeriesUnit": "percent",
        "hub": "3cece1f2bb4e49efa22d45bc34076805",
        "dashboard": "",
        "slice_dimensions": {},
        "data_values": [
            "7.09",
            "6.69",
            "8.13",
            "7.34",
            "14.78",
            "8.14",
            "8.96",
            "3.94",
            "9.03",
            "10.22",
            "9.16",
            "9.55",
            "7.7",
            "9.38",
            "8.74",
            "12.6",
            "14.17",
            "13.06"
        ],
        "data_years": [
            2000,
            2001,
            2002,
            2003,
            2004,
            2005,
            2006,
            2007,
            2008,
            2009,
            2010,
            2011,
            2012,
            2013,
            2014,
            2015,
            2016,
            2017
        ],
        "data_is_censored": [
            false,
            false,
            false,
            false,
            false,
            false,
            false,
            false,
            false,
            false,
            false,
            false,
            false,
            false,
            false,
            false,
            false,
            false
        ],
        "data_numeric_part": [
            7.09,
            6.69,
            8.13,
            7.34,
            14.78,
            8.14,
            8.96,
            3.94,
            9.03,
            10.22,
            9.16,
            9.55,
            7.7,
            9.38,
            8.74,
            12.6,
            14.17,
            13.06
        ],
        "preferred_visualization": null
    },
    {
        "release": "2020.Q2.G.03",
        "country_code": "654",
        "country_name": "Saint Helena",
        "indicator_code": "C070a01",
        "indicator_reference": "7.a.1",
        "seriesCode": "EG_IFF_RANDN",
        "seriesDescription": "International financial flows to developing countries in support of clean energy research and development and renewable energy production, including in hybrid systems (millions of constant 2017 United States dollars)",
        "timeSeriesTitle": "International financial flows in support of clean energy research and development and renewable energy production, including in hybrid systems ",
        "timeSeriesUnit": "millions of constant 2017 dollars",
        "hub": "086d631bf5ef4a96aedb07238346e343",
        "dashboard": "",
        "slice_dimensions": {},
        "data_values": [
            "0.16",
            "0.12",
            "1.37"
        ],
        "data_years": [
            2003,
            2008,
            2015
        ],
        "data_is_censored": [
            false,
            false,
            false
        ],
        "data_numeric_part": [
            0.16,
            0.12,
            1.37
        ],
        "preferred_visualization": null
    },
    {
        "release": "2020.Q2.G.03",
        "country_code": "654",
        "country_name": "Saint Helena",
        "indicator_code": "C080a01",
        "indicator_reference": "8.a.1",
        "seriesCode": "DC_TOF_TRDDBML",
        "seriesDescription": "Total official flows (disbursement) for Aid for Trade, by recipient countries (millions of constant 2018 United States dollars)",
        "timeSeriesTitle": "Total official flows (disbursement) for Aid for Trade, as recipient",
        "timeSeriesUnit": "millions of constant 2018 dollars",
        "hub": "5106611c6f4a4b62a7e8d7fe5e54b34b",
        "dashboard": "",
        "slice_dimensions": {},
        "data_values": [
            "8.95624",
            "7.34552",
            "25.71751",
            "15.24485",
            "8.92069",
            "70.49284",
            "134.552",
            "87.37868",
            "72.4776",
            "44.8481",
            "47.06527",
            "26.53024",
            "23.78044"
        ],
        "data_years": [
            2006,
            2007,
            2008,
            2009,
            2010,
            2011,
            2012,
            2013,
            2014,
            2015,
            2016,
            2017,
            2018
        ],
        "data_is_censored": [
            false,
            false,
            false,
            false,
            false,
            false,
            false,
            false,
            false,
            false,
            false,
            false,
            false
        ],
        "data_numeric_part": [
            8.95624,
            7.34552,
            25.71751,
            15.24485,
            8.92069,
            70.49284,
            134.552,
            87.37868,
            72.4776,
            44.8481,
            47.06527,
            26.53024,
            23.78044
        ],
        "preferred_visualization": null
    },
    {
        "release": "2020.Q2.G.03",
        "country_code": "654",
        "country_name": "Saint Helena",
        "indicator_code": "C080a01",
        "indicator_reference": "8.a.1",
        "seriesCode": "DC_TOF_TRDCML",
        "seriesDescription": "Total official flows (commitments) for Aid for Trade, by recipient countries (millions of constant 2018 United States dollars)",
        "timeSeriesTitle": "Total official flows (commitments) for Aid for Trade, as recipient",
        "timeSeriesUnit": "millions of constant 2018 dollars",
        "hub": "30d25ad9687146008aa05e8b4cd18eaf",
        "dashboard": "",
        "slice_dimensions": {},
        "data_values": [
            "38.53767",
            "21.5744",
            "5.37627",
            "15.59812",
            "21.83488",
            "8.14382",
            "60.30112",
            "8.46476",
            "19.69609",
            "11.391",
            "25.47496",
            "86.55312",
            "4.06422",
            "25.37472"
        ],
        "data_years": [
            2005,
            2006,
            2007,
            2008,
            2009,
            2010,
            2011,
            2012,
            2013,
            2014,
            2015,
            2016,
            2017,
            2018
        ],
        "data_is_censored": [
            false,
            false,
            false,
            false,
            false,
            false,
            false,
            false,
            false,
            false,
            false,
            false,
            false,
            false
        ],
        "data_numeric_part": [
            38.53767,
            21.5744,
            5.37627,
            15.59812,
            21.83488,
            8.14382,
            60.30112,
            8.46476,
            19.69609,
            11.391,
            25.47496,
            86.55312,
            4.06422,
            25.37472
        ],
        "preferred_visualization": null
    },
    {
        "release": "2020.Q2.G.03",
        "country_code": "654",
        "country_name": "Saint Helena",
        "indicator_code": "C090102",
        "indicator_reference": "9.1.2",
        "seriesCode": "IS_RDP_FRGVOL",
        "seriesDescription": "Freight volume, by mode of transport (tonne kilometres)",
        "timeSeriesTitle": "Freight volume by road transport",
        "timeSeriesUnit": "tonne kilometres",
        "hub": "4a5d7189e27148c48f045729ef9e40c8",
        "dashboard": "",
        "slice_dimensions": {
            "modeOfTransportation_code": "MOT_ROA"
        },
        "data_values": [
            "0.0"
        ],
        "data_years": [
            2018
        ],
        "data_is_censored": [
            false
        ],
        "data_numeric_part": [
            0.0
        ],
        "preferred_visualization": null
    },
    {
        "release": "2020.Q2.G.03",
        "country_code": "654",
        "country_name": "Saint Helena",
        "indicator_code": "C090502",
        "indicator_reference": "9.5.2",
        "seriesCode": "GB_POP_SCIERD",
        "seriesDescription": "Researchers (in full-time equivalent) per million inhabitants (per 1,000,000 population)",
        "timeSeriesTitle": "Researchers density",
        "timeSeriesUnit": "full-time researchers per million inhabitants",
        "hub": "3e25618c80ff47c9baf740b27b972673",
        "dashboard": "",
        "slice_dimensions": {},
        "data_values": [
            "330.63316"
        ],
        "data_years": [
            2000
        ],
        "data_is_censored": [
            false
        ],
        "data_numeric_part": [
            330.63316
        ],
        "preferred_visualization": null
    },
    {
        "release": "2020.Q2.G.03",
        "country_code": "654",
        "country_name": "Saint Helena",
        "indicator_code": "C090c01",
        "indicator_reference": "9.c.1",
        "seriesCode": "IT_MOB_2GNTWK",
        "seriesDescription": "Proportion of population covered by at least a 2G mobile network (%)",
        "timeSeriesTitle": "Proportion of population covered by at least a 2G mobile network",
        "timeSeriesUnit": "percent",
        "hub": "9c0472e1e3cb453b881e639385c43934",
        "dashboard": "",
        "slice_dimensions": {},
        "data_values": [
            "0.0",
            "0.0",
            "0.0",
            "0.0",
            "0.0",
            "98.0",
            "98.0",
            "98.0"
        ],
        "data_years": [
            2002,
            2003,
            2004,
            2005,
            2006,
            2015,
            2016,
            2017
        ],
        "data_is_censored": [
            false,
            false,
            false,
            false,
            false,
            false,
            false,
            false
        ],
        "data_numeric_part": [
            0.0,
            0.0,
            0.0,
            0.0,
            0.0,
            98.0,
            98.0,
            98.0
        ],
        "preferred_visualization": null
    },
    {
        "release": "2020.Q2.G.03",
        "country_code": "654",
        "country_name": "Saint Helena",
        "indicator_code": "C090c01",
        "indicator_reference": "9.c.1",
        "seriesCode": "IT_MOB_3GNTWK",
        "seriesDescription": "Proportion of population covered by at least a 3G mobile network (%)",
        "timeSeriesTitle": "Proportion of population covered by at least a 3G mobile network",
        "timeSeriesUnit": "percent",
        "hub": "749fd00904e14ff5bd005d5805b0db24",
        "dashboard": "",
        "slice_dimensions": {},
        "data_values": [
            "95.0",
            "97.0",
            "97.0"
        ],
        "data_years": [
            2015,
            2016,
            2017
        ],
        "data_is_censored": [
            false,
            false,
            false
        ],
        "data_numeric_part": [
            95.0,
            97.0,
            97.0
        ],
        "preferred_visualization": null
    },
    {
        "release": "2020.Q2.G.03",
        "country_code": "654",
        "country_name": "Saint Helena",
        "indicator_code": "C090c01",
        "indicator_reference": "9.c.1",
        "seriesCode": "IT_MOB_4GNTWK",
        "seriesDescription": "Proportion of population covered by at least a 4G mobile network (%)",
        "timeSeriesTitle": "Proportion of population covered by at least a 4G mobile network",
        "timeSeriesUnit": "percent",
        "hub": "6b2807560f6e4b9a8338bbd501dfba31",
        "dashboard": "",
        "slice_dimensions": {},
        "data_values": [
            "90.0",
            "97.0",
            "97.0"
        ],
        "data_years": [
            2015,
            2016,
            2017
        ],
        "data_is_censored": [
            false,
            false,
            false
        ],
        "data_numeric_part": [
            90.0,
            97.0,
            97.0
        ],
        "preferred_visualization": null
    },
    {
        "release": "2020.Q2.G.03",
        "country_code": "654",
        "country_name": "Saint Helena",
        "indicator_code": "C100a01",
        "indicator_reference": "10.a.1",
        "seriesCode": "TM_TRF_ZERO",
        "seriesDescription": "Proportion of tariff lines applied to imports with zero-tariff (%)",
        "timeSeriesTitle": "Proportion of tariff lines applied to imports with zero-tariff",
        "timeSeriesUnit": "percent",
        "hub": "60d8d0090395422a9fe62177fe8e7cd7",
        "dashboard": "",
        "slice_dimensions": {
            "typeOfProduct_code": "_T"
        },
        "data_values": [
            "42.6506",
            "33.63914",
            "66.35945",
            "49.29078",
            "58.95062",
            "59.5679"
        ],
        "data_years": [
            2005,
            2010,
            2015,
            2016,
            2017,
            2018
        ],
        "data_is_censored": [
            false,
            false,
            false,
            false,
            false,
            false
        ],
        "data_numeric_part": [
            42.6506,
            33.63914,
            66.35945,
            49.29078,
            58.95062,
            59.5679
        ],
        "preferred_visualization": null
    },
    {
        "release": "2020.Q2.G.03",
        "country_code": "654",
        "country_name": "Saint Helena",
        "indicator_code": "C140501",
        "indicator_reference": "14.5.1",
        "seriesCode": "ER_MRN_MARINT",
        "seriesDescription": "Protected marine area (Exclusive Economic Zones) (square kilometres)",
        "timeSeriesTitle": "Protected marine area (Exclusive Economic Zones)",
        "timeSeriesUnit": "square kilometres",
        "hub": "be1eb5aebdf24e43a91a769e3d6fbd2b",
        "dashboard": "",
        "slice_dimensions": {},
        "data_values": [
            "448524.20403"
        ],
        "data_years": [
            2018
        ],
        "data_is_censored": [
            false
        ],
        "data_numeric_part": [
            448524.20403
        ],
        "preferred_visualization": null
    },
    {
        "release": "2020.Q2.G.03",
        "country_code": "654",
        "country_name": "Saint Helena",
        "indicator_code": "C140501",
        "indicator_reference": "14.5.1",
        "seriesCode": "ER_MRN_MARIN",
        "seriesDescription": "Coverage of protected areas in relation to marine areas (Exclusive Economic Zones) (%)",
        "timeSeriesTitle": "Coverage of protected areas in relation to marine areas (Exclusive Economic Zones)",
        "timeSeriesUnit": "percent",
        "hub": "1a4acac4d7284c75a48b7c5d07dfdc36",
        "dashboard": "",
        "slice_dimensions": {},
        "data_values": [
            "27.22048"
        ],
        "data_years": [
            2018
        ],
        "data_is_censored": [
            false
        ],
        "data_numeric_part": [
            27.22048
        ],
        "preferred_visualization": null
    },
    {
        "release": "2020.Q2.G.03",
        "country_code": "654",
        "country_name": "Saint Helena",
        "indicator_code": "C150101",
        "indicator_reference": "15.1.1",
        "seriesCode": "AG_LND_TOTL",
        "seriesDescription": "Land area (thousands of hectares)",
        "timeSeriesTitle": "Land area",
        "timeSeriesUnit": "thousands of hectares",
        "hub": "9a4a60e678a94e3e8f44655e7e4bd4f6",
        "dashboard": "",
        "slice_dimensions": {},
        "data_values": [
            "39.0"
        ],
        "data_years": [
            2015
        ],
        "data_is_censored": [
            false
        ],
        "data_numeric_part": [
            39.0
        ],
        "preferred_visualization": null
    },
    {
        "release": "2020.Q2.G.03",
        "country_code": "654",
        "country_name": "Saint Helena",
        "indicator_code": "C150101",
        "indicator_reference": "15.1.1",
        "seriesCode": "AG_LND_FRSTN",
        "seriesDescription": "Forest area (thousands of hectares)",
        "timeSeriesTitle": "Forest area",
        "timeSeriesUnit": "thousands of hectares",
        "hub": "09f04174488d4f8fabceddb8e2920dae",
        "dashboard": "",
        "slice_dimensions": {},
        "data_values": [
            "2.0",
            "2.0",
            "2.0",
            "2.0",
            "2.0",
            "2.0",
            "2.0",
            "2.0"
        ],
        "data_years": [
            2000,
            2010,
            2015,
            2016,
            2017,
            2018,
            2019,
            2020
        ],
        "data_is_censored": [
            false,
            false,
            false,
            false,
            false,
            false,
            false,
            false
        ],
        "data_numeric_part": [
            2.0,
            2.0,
            2.0,
            2.0,
            2.0,
            2.0,
            2.0,
            2.0
        ],
        "preferred_visualization": null
    },
    {
        "release": "2020.Q2.G.03",
        "country_code": "654",
        "country_name": "Saint Helena",
        "indicator_code": "C150101",
        "indicator_reference": "15.1.1",
        "seriesCode": "AG_LND_FRST",
        "seriesDescription": "Forest area as a proportion of total land area (%)",
        "timeSeriesTitle": "Forest area as a proportion of total land area",
        "timeSeriesUnit": "percent",
        "hub": "4787e933dac34421b4b11427a0b78fbe",
        "dashboard": "",
        "slice_dimensions": {},
        "data_values": [
            "5.12820512820513",
            "5.12820512820513",
            "5.12820512820513",
            "5.12820512820513",
            "5.12820512820513",
            "5.12820512820513",
            "5.12820512820513",
            "5.12820512820513"
        ],
        "data_years": [
            2000,
            2010,
            2015,
            2016,
            2017,
            2018,
            2019,
            2020
        ],
        "data_is_censored": [
            false,
            false,
            false,
            false,
            false,
            false,
            false,
            false
        ],
        "data_numeric_part": [
            5.12820512820513,
            5.12820512820513,
            5.12820512820513,
            5.12820512820513,
            5.12820512820513,
            5.12820512820513,
            5.12820512820513,
            5.12820512820513
        ],
        "preferred_visualization": null
    },
    {
        "release": "2020.Q2.G.03",
        "country_code": "654",
        "country_name": "Saint Helena",
        "indicator_code": "C150201",
        "indicator_reference": "15.2.1",
        "seriesCode": "AG_LND_FRSTCERT",
        "seriesDescription": "Forest area under an independently verified forest management certification scheme (thousands of hectares)",
        "timeSeriesTitle": "Forest area under an independently verified forest management certification scheme",
        "timeSeriesUnit": "thousands of hectares",
        "hub": "13a621d222c243dc906d7ee53d13eff3",
        "dashboard": "",
        "slice_dimensions": {},
        "data_values": [
            "0.0",
            "0.0",
            "0.0",
            "0.0",
            "0.0",
            "0.0",
            "0.0",
            "0.0"
        ],
        "data_years": [
            2000,
            2005,
            2010,
            2015,
            2016,
            2017,
            2018,
            2019
        ],
        "data_is_censored": [
            false,
            false,
            false,
            false,
            false,
            false,
            false,
            false
        ],
        "data_numeric_part": [
            0.0,
            0.0,
            0.0,
            0.0,
            0.0,
            0.0,
            0.0,
            0.0
        ],
        "preferred_visualization": null
    },
    {
        "release": "2020.Q2.G.03",
        "country_code": "654",
        "country_name": "Saint Helena",
        "indicator_code": "C150201",
        "indicator_reference": "15.2.1",
        "seriesCode": "AG_LND_FRSTCHG",
        "seriesDescription": "Forest area annual net change rate (%)",
        "timeSeriesTitle": "Forest area annual net change rate",
        "timeSeriesUnit": "percent",
        "hub": "494e02b3371a4a48acc40fbefc23e7ae",
        "dashboard": "",
        "slice_dimensions": {},
        "data_values": [
            "0.0",
            "0.0",
            "0.0"
        ],
        "data_years": [
            2010,
            2015,
            2020
        ],
        "data_is_censored": [
            false,
            false,
            false
        ],
        "data_numeric_part": [
            0.0,
            0.0,
            0.0
        ],
        "preferred_visualization": null
    },
    {
        "release": "2020.Q2.G.03",
        "country_code": "654",
        "country_name": "Saint Helena",
        "indicator_code": "C150601",
        "indicator_reference": "15.6.1",
        "seriesCode": "ER_CBD_SMTA",
        "seriesDescription": "Total reported number of Standard Material Transfer Agreements (SMTAs) transferring plant genetic resources for food and agriculture to the country (number)",
        "timeSeriesTitle": "Total reported number of Standard Material Transfer Agreements (SMTAs) transferring plant genetic resources for food and agriculture to the country",
        "timeSeriesUnit": "agreements",
        "hub": "0765d85f3d504a03ad69a5a773b62e3d",
        "dashboard": "",
        "slice_dimensions": {},
        "data_values": [
            "0.0",
            "0.0",
            "0.0",
            "0.0",
            "0.0",
            "0.0",
            "0.0",
            "0.0"
        ],
        "data_years": [
            2012,
            2013,
            2014,
            2015,
            2016,
            2017,
            2018,
            2019
        ],
        "data_is_censored": [
            false,
            false,
            false,
            false,
            false,
            false,
            false,
            false
        ],
        "data_numeric_part": [
            0.0,
            0.0,
            0.0,
            0.0,
            0.0,
            0.0,
            0.0,
            0.0
        ],
        "preferred_visualization": null
    },
    {
        "release": "2020.Q2.G.03",
        "country_code": "654",
        "country_name": "Saint Helena",
        "indicator_code": "C150601",
        "indicator_reference": "15.6.1",
        "seriesCode": "ER_CBD_ORSPGRFA",
        "seriesDescription": "Countries that have legislative, administrative and policy framework or measures reported through the Online Reporting System on Compliance of the International Treaty on Plant Genetic Resources for Food and Agriculture (PGRFA) (1 = YES; 0 = NO)",
        "timeSeriesTitle": "Existence of legislative, administrative and policy framework or measures reported through the Online Reporting System on Compliance  of the International Treaty on Plant Genetic Resources for Food and Agriculture (PGRFA) (1 = YES; 0 = NO)",
        "timeSeriesUnit": "yes/no",
        "hub": "06e4982ff3ea4b7aa8af6b2ec2a86951",
        "dashboard": "",
        "slice_dimensions": {},
        "data_values": [
            "0.0",
            "0.0",
            "0.0",
            "0.0"
        ],
        "data_years": [
            2016,
            2017,
            2018,
            2019
        ],
        "data_is_censored": [
            false,
            false,
            false,
            false
        ],
        "data_numeric_part": [
            0.0,
            0.0,
            0.0,
            0.0
        ],
        "preferred_visualization": null
    },
    {
        "release": "2020.Q2.G.03",
        "country_code": "654",
        "country_name": "Saint Helena",
        "indicator_code": "C150601",
        "indicator_reference": "15.6.1",
        "seriesCode": "ER_CBD_PTYPGRFA",
        "seriesDescription": "Countries that are contracting Parties to the International Treaty on Plant Genetic Resources for Food and Agriculture (PGRFA) (1 = YES; 0 = NO)",
        "timeSeriesTitle": "Country is contracting Party to the International Treaty on Plant Genetic Resources for Food and Agriculture (PGRFA) (1 = YES; 0 = NO)",
        "timeSeriesUnit": "yes/no",
        "hub": "d77c1391000b4750adb975bf39970133",
        "dashboard": "",
        "slice_dimensions": {},
        "data_values": [
            "0.0",
            "0.0",
            "0.0",
            "0.0",
            "0.0",
            "0.0",
            "0.0",
            "0.0"
        ],
        "data_years": [
            2012,
            2013,
            2014,
            2015,
            2016,
            2017,
            2018,
            2019
        ],
        "data_is_censored": [
            false,
            false,
            false,
            false,
            false,
            false,
            false,
            false
        ],
        "data_numeric_part": [
            0.0,
            0.0,
            0.0,
            0.0,
            0.0,
            0.0,
            0.0,
            0.0
        ],
        "preferred_visualization": null
    },
    {
        "release": "2020.Q2.G.03",
        "country_code": "654",
        "country_name": "Saint Helena",
        "indicator_code": "C160601",
        "indicator_reference": "16.6.1",
        "seriesCode": "GF_XPD_GBPC",
        "seriesDescription": "Primary government expenditures as a proportion of original approved budget (%)",
        "timeSeriesTitle": "Primary government expenditures as a proportion of original approved budget",
        "timeSeriesUnit": "percent",
        "hub": "dd7c8bf40a1943d7afd3400ac581bb6d",
        "dashboard": "",
        "slice_dimensions": {},
        "data_values": [
            "99.74",
            "99.96",
            "96.56"
        ],
        "data_years": [
            2011,
            2012,
            2013
        ],
        "data_is_censored": [
            false,
            false,
            false
        ],
        "data_numeric_part": [
            99.74,
            99.96,
            96.56
        ],
        "preferred_visualization": null
    },
    {
        "release": "2020.Q2.G.03",
        "country_code": "654",
        "country_name": "Saint Helena",
        "indicator_code": "C170303",
        "indicator_reference": "17.3.1",
        "seriesCode": "GF_FRN_FDI",
        "seriesDescription": "Foreign direct investment (FDI) inflows (millions of US dollars)",
        "timeSeriesTitle": "Foreign direct investment (FDI) inflows",
        "timeSeriesUnit": "millions of dollars",
        "hub": "934e2d3838594f97b0f6f4cb614e4fe2",
        "dashboard": "",
        "slice_dimensions": {},
        "data_values": [
            "-3.84",
            "0.23",
            "-0.65",
            "0.18",
            "0.06",
            "0.39"
        ],
        "data_years": [
            2000,
            2001,
            2004,
            2005,
            2006,
            2007
        ],
        "data_is_censored": [
            false,
            false,
            false,
            false,
            false,
            false
        ],
        "data_numeric_part": [
            -3.84,
            0.23,
            -0.65,
            0.18,
            0.06,
            0.39
        ],
        "preferred_visualization": null
    },
    {
        "release": "2020.Q2.G.03",
        "country_code": "654",
        "country_name": "Saint Helena",
        "indicator_code": "C170602",
        "indicator_reference": "17.6.1",
        "seriesCode": "IT_NET_BBN",
        "seriesDescription": "Number of fixed Internet broadband subscriptions, by speed (number)",
        "timeSeriesTitle": "Number of fixed Internet broadband subscriptions",
        "timeSeriesUnit": "subscriptions",
        "hub": "2074500fc50f4966a1bcc01bfa3944cf",
        "dashboard": "",
        "slice_dimensions": {
            "typeOfSpeed_code": "_T"
        },
        "data_values": [
            "3.0",
            "12.0",
            "15.0",
            "16.0",
            "20.0",
            "224.0",
            "415.0",
            "537.0",
            "799.0",
            "282.0",
            "1107.0",
            "1245.0",
            "1337.0",
            "1347.0",
            "1000.0"
        ],
        "data_years": [
            2003,
            2004,
            2005,
            2006,
            2007,
            2008,
            2009,
            2010,
            2011,
            2012,
            2013,
            2014,
            2015,
            2016,
            2017
        ],
        "data_is_censored": [
            false,
            false,
            false,
            false,
            false,
            false,
            false,
            false,
            false,
            false,
            false,
            false,
            false,
            false,
            false
        ],
        "data_numeric_part": [
            3.0,
            12.0,
            15.0,
            16.0,
            20.0,
            224.0,
            415.0,
            537.0,
            799.0,
            282.0,
            1107.0,
            1245.0,
            1337.0,
            1347.0,
            1000.0
        ],
        "preferred_visualization": null
    },
    {
        "release": "2020.Q2.G.03",
        "country_code": "654",
        "country_name": "Saint Helena",
        "indicator_code": "C170602",
        "indicator_reference": "17.6.1",
        "seriesCode": "IT_NET_BBP",
        "seriesDescription": "Fixed Internet broadband subscriptions per 100\u00c2 inhabitants, by speed (per 100 inhabitants)",
        "timeSeriesTitle": "Fixed Internet broadband subscriptions per 100\u00a0inhabitants",
        "timeSeriesUnit": "subscriptions",
        "hub": "0d2420834ee949db9e4fddd68f15877e",
        "dashboard": "",
        "slice_dimensions": {
            "typeOfSpeed_code": "_T"
        },
        "data_values": [
            "0.05",
            "0.22",
            "0.28",
            "0.3",
            "0.39",
            "4.36",
            "8.07",
            "10.36",
            "15.13",
            "5.21",
            "19.82",
            "21.69",
            "22.8",
            "22.62",
            "16.64"
        ],
        "data_years": [
            2003,
            2004,
            2005,
            2006,
            2007,
            2008,
            2009,
            2010,
            2011,
            2012,
            2013,
            2014,
            2015,
            2016,
            2017
        ],
        "data_is_censored": [
            false,
            false,
            false,
            false,
            false,
            false,
            false,
            false,
            false,
            false,
            false,
            false,
            false,
            false,
            false
        ],
        "data_numeric_part": [
            0.05,
            0.22,
            0.28,
            0.3,
            0.39,
            4.36,
            8.07,
            10.36,
            15.13,
            5.21,
            19.82,
            21.69,
            22.8,
            22.62,
            16.64
        ],
        "preferred_visualization": null
    },
    {
        "release": "2020.Q2.G.03",
        "country_code": "654",
        "country_name": "Saint Helena",
        "indicator_code": "C170801",
        "indicator_reference": "17.8.1",
        "seriesCode": "IT_USE_ii99",
        "seriesDescription": "Internet users per 100 inhabitants",
        "timeSeriesTitle": "Internet users per 100 inhabitants",
        "timeSeriesUnit": "users",
        "hub": "a2758c4850034da18842ceecaebf240f",
        "dashboard": "",
        "slice_dimensions": {},
        "data_values": [
            "5.922",
            "7.989",
            "10.126",
            "12.338",
            "14.623",
            "15.91",
            "17.227",
            "18.57",
            "18.82",
            "19.07",
            "24.94",
            "33.0",
            "37.6"
        ],
        "data_years": [
            2000,
            2001,
            2002,
            2003,
            2004,
            2005,
            2006,
            2007,
            2008,
            2009,
            2010,
            2011,
            2012
        ],
        "data_is_censored": [
            false,
            false,
            false,
            false,
            false,
            false,
            false,
            false,
            false,
            false,
            false,
            false,
            false
        ],
        "data_numeric_part": [
            5.922,
            7.989,
            10.126,
            12.338,
            14.623,
            15.91,
            17.227,
            18.57,
            18.82,
            19.07,
            24.94,
            33.0,
            37.6
        ],
        "preferred_visualization": null
    },
    {
        "release": "2020.Q2.G.03",
        "country_code": "654",
        "country_name": "Saint Helena",
        "indicator_code": "C171902",
        "indicator_reference": "17.19.2",
        "seriesCode": "SG_REG_CENSUSN",
        "seriesDescription": "Countries that have conducted at least one population and housing census in the last 10 years (1 = YES; 0 = NO)",
        "timeSeriesTitle": "Country has conducted at least one population and housing census in the last 10 years (1 = YES; 0 = NO)",
        "timeSeriesUnit": "yes/no",
        "hub": "5f0fd8d4c1de4b4dbca087786bfc083b",
        "dashboard": "",
        "slice_dimensions": {},
        "data_values": [
            "1.0"
        ],
        "data_years": [
            2016
        ],
        "data_is_censored": [
            false
        ],
        "data_numeric_part": [
            1.0
        ],
        "preferred_visualization": null
    },
    {
        "release": "2020.Q2.G.03",
        "country_code": "654",
        "country_name": "Saint Helena",
        "indicator_code": "C171902",
        "indicator_reference": "17.19.2",
        "seriesCode": "SG_REG_BRTH90N",
        "seriesDescription": "Countries with birth registration data that are at least 90 percent complete (1 = YES; 0 = NO)",
        "timeSeriesTitle": "Existence of birth registration data that are at least 90 percent complete (1 = YES; 0 = NO)",
        "timeSeriesUnit": "yes/no",
        "hub": "19f62e67961a4feb8ffed63e64bb6595",
        "dashboard": "",
        "slice_dimensions": {},
        "data_values": [
            "1.0",
            "1.0",
            "1.0",
            "1.0"
        ],
        "data_years": [
            2015,
            2016,
            2017,
            2018
        ],
        "data_is_censored": [
            false,
            false,
            false,
            false
        ],
        "data_numeric_part": [
            1.0,
            1.0,
            1.0,
            1.0
        ],
        "preferred_visualization": null
    },
    {
        "release": "2020.Q2.G.03",
        "country_code": "654",
        "country_name": "Saint Helena",
        "indicator_code": "C171902",
        "indicator_reference": "17.19.2",
        "seriesCode": "SG_REG_DETH75N",
        "seriesDescription": "Countries with death registration data that are at least 75 percent complete (1 = YES; 0 = NO)",
        "timeSeriesTitle": "Existence of death registration data that are at least 75 percent complete (1 = YES; 0 = NO)",
        "timeSeriesUnit": "yes/no",
        "hub": "86146f7055a048fc9b506a491229192c",
        "dashboard": "",
        "slice_dimensions": {},
        "data_values": [
            "1.0",
            "1.0",
            "1.0",
            "1.0"
        ],
        "data_years": [
            2015,
            2016,
            2017,
            2018
        ],
        "data_is_censored": [
            false,
            false,
            false,
            false
        ],
        "data_numeric_part": [
            1.0,
            1.0,
            1.0,
            1.0
        ],
        "preferred_visualization": null
    }
]